phylo_utils-0.0.10.dist-info/RECORD
phylo_utils-0.0.10.dist-info/WHEEL
phylo_utils-0.0.10.dist-info/top_level.txt
phylo_utils-0.0.10.dist-info/LICENSE.txt
phylo_utils-0.0.10.dist-info/METADATA
phylo_utils/models.py
phylo_utils/markov.py
phylo_utils/__init__.py
phylo_utils/seq_to_partials.py
phylo_utils/likcalc.cpython-310-darwin.so
phylo_utils/likelihood.py
