Metadata-Version: 2.1
Name: phylo-utils
Version: 0.0.10
Summary: Phylogenetics calculations in python
Home-page: 
Author: Kevin Gori
Author-email: kgori@ebi.ac.uk
License-File: LICENSE.txt
Requires-Dist: cython
Requires-Dist: numpy
Requires-Dist: dendropy
